{
  "metadata": {
    "generated_at": "2026-06-10T12:25:43.777759",
    "data_sources": [
      "AlphaVantage",
      "YahooDirect"
    ],
    "total_records": 20,
    "real_data": true,
    "stocks_analyzed": [
      "AAPL",
      "MSFT",
      "TSLA",
      "GOOGL",
      "META",
      "AMZN",
      "NVDA",
      "JPM",
      "V"
    ]
  },
  "results": [
    {
      "Ticker": "AAPL",
      "Company": "Apple Inc.",
      "Headline": "The market hates Siri AI, so it must be good",
      "Headline URL": "https://www.macworld.com/article/3159985/its-apples-ai-party-and-were-all-invited.html",
      "Published At": "2026-06-09T10:45:00Z",
      "Sentiment": "NEUTRAL",
      "Regular Change": -3.64,
      "After Hours": 0.0,
      "Current Price": 290.55,
      "Data Source": "AlphaVantage",
      "News Source": "Macworld",
      "Timestamp": "2026-06-10T12:25:43.776529"
    },
    {
      "Ticker": "AAPL",
      "Company": "Apple Inc.",
      "Headline": "Apple WWDC 2026 keynote event: Live updates on iOS 27 and Siri - Mashable",
      "Headline URL": "https://slashdot.org/firehose.pl?op=view&amp;id=183698908",
      "Published At": "2026-06-09T06:32:46Z",
      "Sentiment": "NEUTRAL",
      "Regular Change": -3.64,
      "After Hours": 0.0,
      "Current Price": 290.55,
      "Data Source": "AlphaVantage",
      "News Source": "Slashdot.org",
      "Timestamp": "2026-06-10T12:25:43.776548"
    },
    {
      "Ticker": "AAPL",
      "Company": "Apple Inc.",
      "Headline": "Redington shares rally 5% after Apple unveils new features at WWDC 2026",
      "Headline URL": "https://economictimes.indiatimes.com/markets/stocks/news/redington-shares-rally-5-after-apple-unveils-new-features-in-wwdc-2026/articleshow/131602912.cms",
      "Published At": "2026-06-09T05:49:01Z",
      "Sentiment": "POSITIVE",
      "Regular Change": -3.64,
      "After Hours": 0.0,
      "Current Price": 290.55,
      "Data Source": "AlphaVantage",
      "News Source": "The Times of India",
      "Timestamp": "2026-06-10T12:25:43.776556"
    },
    {
      "Ticker": "MSFT",
      "Company": "Microsoft Corp.",
      "Headline": "ServiceTitan Stock Surged on Better-Than-Expected Results Powered by AI. What This Means for ServiceTitan Investors.",
      "Headline URL": "https://www.barchart.com/story/news/2365615/servicetitan-stock-surged-on-better-than-expected-results-powered-by-ai-what-this-means-for-servicetitan-investors",
      "Published At": "2026-06-08T20:52:28Z",
      "Sentiment": "NEUTRAL",
      "Regular Change": -2.02,
      "After Hours": 0.0,
      "Current Price": 403.41,
      "Data Source": "YahooDirect",
      "News Source": "Barchart.com",
      "Timestamp": "2026-06-10T12:25:43.776567"
    },
    {
      "Ticker": "MSFT",
      "Company": "Microsoft Corp.",
      "Headline": "Microsoft (MSFT) Signals Ambitions to Join the Top Tier of AI Labs",
      "Headline URL": "https://consent.yahoo.com/v2/collectConsent?sessionId=1_cc-session_21f6f11a-90e7-4cec-b0ac-ad821c85f6a2",
      "Published At": "2026-06-08T17:12:14Z",
      "Sentiment": "NEUTRAL",
      "Regular Change": -2.02,
      "After Hours": 0.0,
      "Current Price": 403.41,
      "Data Source": "YahooDirect",
      "News Source": "Yahoo Entertainment",
      "Timestamp": "2026-06-10T12:25:43.776582"
    },
    {
      "Ticker": "TSLA",
      "Company": "Tesla Inc.",
      "Headline": "Short-sellers to tread carefully as Musk's SpaceX debuts",
      "Headline URL": "https://www.thehindubusinessline.com/markets/short-sellers-to-tread-carefully-as-musks-spacex-debuts/article71080224.ece",
      "Published At": "2026-06-09T10:33:12Z",
      "Sentiment": "NEUTRAL",
      "Regular Change": -3.0,
      "After Hours": 0.0,
      "Current Price": 396.68,
      "Data Source": "AlphaVantage",
      "News Source": "BusinessLine",
      "Timestamp": "2026-06-10T12:25:43.776593"
    },
    {
      "Ticker": "TSLA",
      "Company": "Tesla Inc.",
      "Headline": "JPMorgan Just Dramatically Reversed Course on Tesla Because TSLA Stock Has Massive Physical AI Potential",
      "Headline URL": "https://www.barchart.com/story/news/2364068/jpmorgan-just-dramatically-reversed-course-on-tesla-because-tsla-stock-has-massive-physical-ai-potential",
      "Published At": "2026-06-08T19:41:05Z",
      "Sentiment": "NEUTRAL",
      "Regular Change": -3.0,
      "After Hours": 0.0,
      "Current Price": 396.68,
      "Data Source": "AlphaVantage",
      "News Source": "Barchart.com",
      "Timestamp": "2026-06-10T12:25:43.776605"
    },
    {
      "Ticker": "TSLA",
      "Company": "Tesla Inc.",
      "Headline": "At a $1.2 Trillion Market Cap, Is Tesla Stock Overvalued or Undervalued Right Now?",
      "Headline URL": "https://consent.yahoo.com/v2/collectConsent?sessionId=1_cc-session_3744fe8e-ca6a-4441-b25e-bd0f9edcff46",
      "Published At": "2026-06-08T16:35:00Z",
      "Sentiment": "NEUTRAL",
      "Regular Change": -3.0,
      "After Hours": 0.0,
      "Current Price": 396.68,
      "Data Source": "AlphaVantage",
      "News Source": "Yahoo Entertainment",
      "Timestamp": "2026-06-10T12:25:43.776619"
    },
    {
      "Ticker": "GOOGL",
      "Company": "Alphabet Inc.",
      "Headline": "SpaceX, Google compute deal raises eyebrows ahead of IPO",
      "Headline URL": "https://finance.yahoo.com/markets/stocks/article/spacex-google-compute-deal-raises-eyebrows-ahead-of-ipo-120522033.html",
      "Published At": "2026-06-09T12:05:22Z",
      "Sentiment": "POSITIVE",
      "Regular Change": 0.26,
      "After Hours": 0.0,
      "Current Price": 364.26,
      "Data Source": "YahooDirect",
      "News Source": "Yahoo Entertainment",
      "Timestamp": "2026-06-10T12:25:43.776629"
    },
    {
      "Ticker": "GOOGL",
      "Company": "Alphabet Inc.",
      "Headline": "The Liquidity Vacuum: Why Friday\u2019s Stock Market Selloff Was a Technical Glitch",
      "Headline URL": "https://www.barchart.com/story/news/2364732/the-liquidity-vacuum-why-fridays-stock-market-selloff-was-a-technical-glitch",
      "Published At": "2026-06-08T20:13:56Z",
      "Sentiment": "NEUTRAL",
      "Regular Change": 0.26,
      "After Hours": 0.0,
      "Current Price": 364.26,
      "Data Source": "YahooDirect",
      "News Source": "Barchart.com",
      "Timestamp": "2026-06-10T12:25:43.776643"
    },
    {
      "Ticker": "GOOGL",
      "Company": "Alphabet Inc.",
      "Headline": "What You Missed About Google Stock Right Before It Went 2x",
      "Headline URL": "https://consent.yahoo.com/v2/collectConsent?sessionId=1_cc-session_f5673c5a-024e-48f0-aed6-6574b2096bb9",
      "Published At": "2026-06-08T20:03:04Z",
      "Sentiment": "NEGATIVE",
      "Regular Change": 0.26,
      "After Hours": 0.0,
      "Current Price": 364.26,
      "Data Source": "YahooDirect",
      "News Source": "Yahoo Entertainment",
      "Timestamp": "2026-06-10T12:25:43.776652"
    },
    {
      "Ticker": "META",
      "Company": "Meta Platforms",
      "Headline": "Meta considers raising billions in equity after Alphabet\u2019s record $85B share sale",
      "Headline URL": "https://cryptobriefing.com/meta-equity-raise-alphabet-85b-sale/",
      "Published At": "2026-06-07T07:13:24Z",
      "Sentiment": "POSITIVE",
      "Regular Change": -0.14,
      "After Hours": 0.0,
      "Current Price": 584.59,
      "Data Source": "AlphaVantage",
      "News Source": "Crypto Briefing",
      "Timestamp": "2026-06-10T12:25:43.776664"
    },
    {
      "Ticker": "AMZN",
      "Company": "Amazon.com Inc.",
      "Headline": "Monkeys Magic Merry Go Round 2024 1080p AMZN WEB-DL H264-BobDobbs",
      "Headline URL": "https://post.rlsbb.to/monkeys-magic-merry-go-round-2024-1080p-amzn-web-dl-h264-bobdobbs/",
      "Published At": "2026-06-09T09:09:00Z",
      "Sentiment": "NEUTRAL",
      "Regular Change": -0.42,
      "After Hours": 0.0,
      "Current Price": 244.19,
      "Data Source": "YahooDirect",
      "News Source": "Rlsbb.to",
      "Timestamp": "2026-06-10T12:25:43.776674"
    },
    {
      "Ticker": "AMZN",
      "Company": "Amazon.com Inc.",
      "Headline": "Personhood 2025 720p AMZN WEB-DL H264-BYNDR",
      "Headline URL": "https://post.rlsbb.to/personhood-2025-720p-amzn-web-dl-h264-byndr/",
      "Published At": "2026-06-09T08:54:19Z",
      "Sentiment": "NEUTRAL",
      "Regular Change": -0.42,
      "After Hours": 0.0,
      "Current Price": 244.19,
      "Data Source": "YahooDirect",
      "News Source": "Rlsbb.to",
      "Timestamp": "2026-06-10T12:25:43.776681"
    },
    {
      "Ticker": "AMZN",
      "Company": "Amazon.com Inc.",
      "Headline": "Neglected 2025 720p AMZN WEB-DL H264-BYNDR",
      "Headline URL": "https://post.rlsbb.to/neglected-2025-720p-amzn-web-dl-h264-byndr/",
      "Published At": "2026-06-09T08:54:19Z",
      "Sentiment": "NEUTRAL",
      "Regular Change": -0.42,
      "After Hours": 0.0,
      "Current Price": 244.19,
      "Data Source": "YahooDirect",
      "News Source": "Rlsbb.to",
      "Timestamp": "2026-06-10T12:25:43.776688"
    },
    {
      "Ticker": "NVDA",
      "Company": "NVIDIA Corp.",
      "Headline": "Why are ASX 200 tech stocks like WiseTech, Life360 and Xero shares getting hammered on Tuesday?",
      "Headline URL": "https://www.fool.com.au/2026/06/09/why-are-asx-200-tech-stocks-like-wisetech-life360-and-xero-shares-getting-hammered-on-tuesday/",
      "Published At": "2026-06-09T01:10:12Z",
      "Sentiment": "NEUTRAL",
      "Regular Change": -0.22,
      "After Hours": 0.0,
      "Current Price": 208.19,
      "Data Source": "AlphaVantage",
      "News Source": "Motley Fool Australia",
      "Timestamp": "2026-06-10T12:25:43.776701"
    },
    {
      "Ticker": "JPM",
      "Company": "JPMorgan Chase",
      "Headline": "This Analyst Just Upgraded Chipotle Stock. Here's Why.",
      "Headline URL": "https://www.barchart.com/story/news/2360302/this-analyst-just-upgraded-chipotle-stock-here-s-why",
      "Published At": "2026-06-08T15:53:30Z",
      "Sentiment": "POSITIVE",
      "Regular Change": 0.51,
      "After Hours": 0.0,
      "Current Price": 312.7,
      "Data Source": "YahooDirect",
      "News Source": "Barchart.com",
      "Timestamp": "2026-06-10T12:25:43.776710"
    },
    {
      "Ticker": "V",
      "Company": "Visa Inc.",
      "Headline": "Obama-appointed judge who blocked Trump birthright citizenship order strikes again, throws out visa overhaul",
      "Headline URL": "https://www.foxnews.com/politics/obama-appointed-judge-blocked-trump-birthright-citizenship-order-strikes-throws-visa-overhaul",
      "Published At": "2026-06-08T21:02:49Z",
      "Sentiment": "NEUTRAL",
      "Regular Change": 1.68,
      "After Hours": 0.0,
      "Current Price": 325.05,
      "Data Source": "AlphaVantage",
      "News Source": "Fox News",
      "Timestamp": "2026-06-10T12:25:43.776721"
    },
    {
      "Ticker": "V",
      "Company": "Visa Inc.",
      "Headline": "Judge voids Trump's $100,000 fee for new H-1B visas",
      "Headline URL": "https://www.cbsnews.com/news/judge-trump-100000-h1b-visa-fee-policy-tax/",
      "Published At": "2026-06-08T19:35:25Z",
      "Sentiment": "NEUTRAL",
      "Regular Change": 1.68,
      "After Hours": 0.0,
      "Current Price": 325.05,
      "Data Source": "AlphaVantage",
      "News Source": "CBS News",
      "Timestamp": "2026-06-10T12:25:43.776729"
    },
    {
      "Ticker": "V",
      "Company": "Visa Inc.",
      "Headline": "Obama Judge Blocks Trump\u2019s $100,000 H-1B Visa Fee",
      "Headline URL": "https://www.thegatewaypundit.com/2026/06/obama-judge-blocks-trumps-100000-h-1b-visa/",
      "Published At": "2026-06-08T19:20:00Z",
      "Sentiment": "NEUTRAL",
      "Regular Change": 1.68,
      "After Hours": 0.0,
      "Current Price": 325.05,
      "Data Source": "AlphaVantage",
      "News Source": "Thegatewaypundit.com",
      "Timestamp": "2026-06-10T12:25:43.776737"
    }
  ]
}